lta/__init__.py
lta/cli.py
lta/commands/__init__.py
lta/commands/run.py
lta/helpers/__init__.py
lta/helpers/custom_types.py
lta/helpers/data_handling.py
lta/helpers/jaccard.py
lta/helpers/pipeline.py
lta/parser.py
lipidta-3.0.1.dist-info/entry_points.txt
lipidta-3.0.1.dist-info/LICENSE
lipidta-3.0.1.dist-info/WHEEL
lipidta-3.0.1.dist-info/METADATA
lipidta-3.0.1.dist-info/RECORD
