Metadata-Version: 2.1
Name: lipidta
Version: 3.0.1
Summary: Lipid Traffic Analysis
Home-page: https://github.com/IMS-Bio2Core-Facility/LTA
License: MIT
Author: rbpatt2019
Author-email: rb.patterson.cross@gmail.com
Requires-Python: >=3.8.0,<3.11
Classifier: Development Status :: 4 - Beta
Classifier: Environment :: Console
Classifier: Intended Audience :: Science/Research
Classifier: License :: OSI Approved :: MIT License
Classifier: Operating System :: OS Independent
Classifier: Programming Language :: Python
Classifier: Programming Language :: Python :: 3
Classifier: Programming Language :: Python :: 3.10
Classifier: Programming Language :: Python :: 3.8
Classifier: Programming Language :: Python :: 3.9
Classifier: Topic :: Scientific/Engineering
Classifier: Topic :: Scientific/Engineering :: Bio-Informatics
Classifier: Typing :: Typed
Requires-Dist: ConfigArgParse (>=1.5,<2.0)
Requires-Dist: numpy (>=1.22.2,<2.0.0)
Requires-Dist: pandas (>=1.3,<2.0)
Project-URL: Documentation, https://LTA.readthedocs.io/en/latest/
Project-URL: Repository, https://github.com/IMS-Bio2Core-Facility/LTA
